duckling/__init__.py
duckling/dim.py
duckling/duckling.py
duckling/language.py
duckling/wrapper.py
duckling/jars/clj-time-0.8.0.jar
duckling/jars/clojure-1.8.0.jar
duckling/jars/duckling-0.4.23.jar
duckling/jars/joda-time-2.3.jar
duckling/jars/lazymap-3.1.0.jar
duckling/jars/plumbing-0.5.3.jar
duckling/jars/schema-1.0.1.jar
duckling/jars/tools.logging-0.2.6.jar
duckling-1.7.3.dist-info/DESCRIPTION.rst
duckling-1.7.3.dist-info/METADATA
duckling-1.7.3.dist-info/RECORD
duckling-1.7.3.dist-info/WHEEL
duckling-1.7.3.dist-info/metadata.json
duckling-1.7.3.dist-info/top_level.txt
