Metadata-Version: 2.0
Name: duckling
Version: 1.7.3
Summary: A wrapper for wit.ai's Duckling
Home-page: https://github.com/FraBle/python-duckling
Author: Frank Blechschmidt
Author-email: frank.blechschmidt@sap.com
License: Apache License 2.0
Keywords: duckling witai datetime parser parsing nlp
Platform: UNKNOWN
Classifier: Development Status :: 5 - Production/Stable
Classifier: Intended Audience :: Developers
Classifier: Topic :: Software Development :: Libraries
Classifier: License :: OSI Approved :: Apache Software License
Classifier: Programming Language :: Python :: 2
Classifier: Programming Language :: Python :: 2.6
Classifier: Programming Language :: Python :: 2.7
Classifier: Programming Language :: Python :: 3
Classifier: Programming Language :: Python :: 3.3
Classifier: Programming Language :: Python :: 3.4
Classifier: Programming Language :: Python :: 3.5
Classifier: Programming Language :: Python :: 3.6
Requires-Dist: JPype1
Requires-Dist: python-dateutil
Requires-Dist: six
